src/tlv5618_driver.v
// tlv5618_driver.v
module tlv5618_driver (
    input clk,
    input rst_n,

    // to user
    input      [15:0] set_data,
    input             set_go,
    output reg        set_done,

    //to DAC
    output reg DAC_cs_n,
    output reg DAC_sclk,
    output reg DAC_din
);
    parameter CLOCK_FREQ = 50_000_000;
    parameter SRCLK_FREQ = 12_500_000;
    parameter MCNT_DIV = CLOCK_FREQ / (SRCLK_FREQ * 2) - 1;

    //计数器
    reg [ 7:0] div_cnt;
    reg [ 5:0] seq_cnt;
    reg        en_div_cnt;

    //暂存数据 
    reg        r_set_go;
    reg [15:0] r_set_data;

    //暂存set_go
    always @(posedge clk or negedge rst_n) begin
        if (~rst_n) begin
            r_set_go <= 0;
        end
        else begin
            r_set_go <= set_go;
        end
    end

    //暂存set_data
    always @(posedge clk or negedge rst_n) begin
        if (~rst_n) begin
            r_set_data <= 16'd0;
        end
        else begin
            r_set_data <= set_data;
        end
    end

    //分频计数器，实现12.5Mhz下的最小时间单位40ns
    always @(posedge clk or negedge rst_n) begin
        if (~rst_n) begin
            div_cnt <= 0;
        end
        else if (en_div_cnt) begin
            if (div_cnt == MCNT_DIV) begin
                div_cnt <= 0;
            end
            else begin
                div_cnt <= div_cnt + 1;
            end
        end
        else begin
            div_cnt <= 0;
        end
    end

    //序列计数器
    always @(posedge clk or negedge rst_n) begin
        if (~rst_n) begin
            seq_cnt <= 0;
        end
        else if (div_cnt == MCNT_DIV) begin
            if (seq_cnt == 33) begin
                seq_cnt <= 0;
            end
            else begin
                seq_cnt <= seq_cnt + 1;
            end
        end
        else begin
            seq_cnt <= seq_cnt;
        end
    end

    // en_div_cnt 生成信号
    always @(posedge clk or negedge rst_n) begin
        if (~rst_n) begin
            en_div_cnt <= 0;
        end
        else if (set_go) begin
            en_div_cnt <= 1;
        end
        else if ((div_cnt == MCNT_DIV) && (seq_cnt == 33)) begin
            en_div_cnt <= 0;
        end
        else begin
            en_div_cnt <= en_div_cnt;
        end
    end

    //set_done
    always @(posedge clk or negedge rst_n) begin
        if (~rst_n) begin
            set_done <= 0;
        end
        else if ((div_cnt == MCNT_DIV) && (seq_cnt == 33)) begin
            set_done <= 1;
        end
        else begin
            set_done <= 0;
        end
    end
    //序列机实现
    always @(posedge clk or negedge rst_n) begin
        if (~rst_n) begin
            DAC_sclk <= 1;
            DAC_din  <= 0;
            DAC_cs_n <= 1;
        end
        else if (div_cnt == MCNT_DIV) begin
            case (seq_cnt)
                0: begin
                    DAC_cs_n <= 0;
                    DAC_sclk <= 1;
                    DAC_din  <= r_set_data[15];
                end
                1:  DAC_sclk <= 0;
                2: begin
                    DAC_sclk <= 1;
                    DAC_din  <= r_set_data[14];
                end
                3:  DAC_sclk <= 0;
                4: begin
                    DAC_sclk <= 1;
                    DAC_din  <= r_set_data[13];
                end
                5:  DAC_sclk <= 0;
                6: begin
                    DAC_sclk <= 1;
                    DAC_din  <= r_set_data[12];
                end
                7:  DAC_sclk <= 0;
                8: begin
                    DAC_sclk <= 1;
                    DAC_din  <= r_set_data[11];
                end
                9:  DAC_sclk <= 0;
                10: begin
                    DAC_sclk <= 1;
                    DAC_din  <= r_set_data[10];
                end
                11: DAC_sclk <= 0;
                12: begin
                    DAC_sclk <= 1;
                    DAC_din  <= r_set_data[9];
                end
                13: DAC_sclk <= 0;
                14: begin
                    DAC_sclk <= 1;
                    DAC_din  <= r_set_data[8];
                end
                15: DAC_sclk <= 0;
                16: begin
                    DAC_sclk <= 1;
                    DAC_din  <= r_set_data[7];
                end
                17: DAC_sclk <= 0;
                18: begin
                    DAC_sclk <= 1;
                    DAC_din  <= r_set_data[6];
                end
                19: DAC_sclk <= 0;
                20: begin
                    DAC_sclk <= 1;
                    DAC_din  <= r_set_data[5];
                end
                21: DAC_sclk <= 0;
                22: begin
                    DAC_sclk <= 1;
                    DAC_din  <= r_set_data[4];
                end
                23: DAC_sclk <= 0;
                24: begin
                    DAC_sclk <= 1;
                    DAC_din  <= r_set_data[3];
                end
                25: DAC_sclk <= 0;
                26: begin
                    DAC_sclk <= 1;
                    DAC_din  <= r_set_data[2];
                end
                27: DAC_sclk <= 0;
                28: begin
                    DAC_sclk <= 1;
                    DAC_din  <= r_set_data[1];
                end
                29: DAC_sclk <= 0;
                30: begin
                    DAC_sclk <= 1;
                    DAC_din  <= r_set_data[0];
                end
                31: DAC_sclk <= 0;
                32: begin
                    DAC_sclk <= 1;
                    DAC_din  <= 0;
                end
                33: begin
                    DAC_sclk <= 1;
                    DAC_cs_n <= 1;
                end
                default: begin
                    DAC_sclk <= DAC_sclk;
                    DAC_din  <= DAC_din;
                    DAC_cs_n <= DAC_cs_n;
                end
            endcase
        end
        else begin
            DAC_sclk <= DAC_sclk;
            DAC_din  <= DAC_din;
            DAC_cs_n <= DAC_cs_n;
        end
    end


endmodule

src/tlv5618_driver_tb.v
// tlv5618_driver_tb.v
`timescale 1ns / 1ps
module tlv5618_driver_tb;
    reg         clk = 1;
    reg         rst_n;
    // to user
    reg  [15:0] set_data;
    reg         set_go;
    wire        set_done;

    //to DAC
    wire        DAC_cs_n;
    wire        DAC_sclk;
    wire        DAC_din;

    reg [15:0] data;

    always #10 clk = ~clk;

    initial begin
        rst_n<=0;
        set_go<=0;
        set_data<=0;
        #100;
        rst_n=1;
        #50;
        //第一次传输
        set_go=1;
        set_data= 16'b0101_0111_1101_0000;
        #20; 
        set_go=0;
        #200;
        wait(DAC_cs_n);
        #200;
        

        //第二次传输
        set_go=1;
        set_data= 16'b1100_0011_1110_1000;
        #20; 
        set_go=0;
        #200;
        wait(DAC_cs_n);
        #200;
       
        $finish;
    end

    tlv5618_driver u_tlv5618_driver (
        .clk     (clk),
        .rst_n   (rst_n),
        .set_data(set_data),
        .set_go  (set_go),
        .set_done(set_done),
        .DAC_cs_n(DAC_cs_n),
        .DAC_sclk(DAC_sclk),
        .DAC_din (DAC_din)
    );


    initial begin
        $dumpfile("wave.vcd");
        $dumpvars(0, tlv5618_driver_tb);
    end

endmodule

wave.vcd
$date
	Tue May 13 15:43:48 2025
$end
$version
	Icarus Verilog
$end
$timescale
	1ps
$end
$scope module tlv5618_driver_tb $end
$var wire 1 ! set_done $end
$var wire 1 " DAC_sclk $end
$var wire 1 # DAC_din $end
$var wire 1 $ DAC_cs_n $end
$var reg 1 % clk $end
$var reg 1 & rst_n $end
$var reg 16 ' set_data [15:0] $end
$var reg 1 ( set_go $end
$scope module u_tlv5618_driver $end
$var wire 1 % clk $end
$var wire 1 & rst_n $end
$var wire 16 ) set_data [15:0] $end
$var wire 1 ( set_go $end
$var reg 1 $ DAC_cs_n $end
$var reg 1 # DAC_din $end
$var reg 1 " DAC_sclk $end
$var reg 8 * div_cnt [7:0] $end
$var reg 1 + en_div_cnt $end
$var reg 16 , r_set_data [15:0] $end
$var reg 1 - r_set_go $end
$var reg 6 . seq_cnt [5:0] $end
$var reg 1 ! set_done $end
$upscope $end
$upscope $end
$enddefinitions $end
#0
$dumpvars
b0 .
0-
b0 ,
0+
b0 *
b0 )
0(
b0 '
0&
1%
1$
0#
1"
0!
$end
#10000
0%
#20000
1%
#30000
0%
#40000
1%
#50000
0%
#60000
1%
#70000
0%
#80000
1%
#90000
0%
#100000
1%
1&
#110000
0%
#120000
1%
#130000
0%
#140000
1%
#150000
0%
b101011111010000 '
b101011111010000 )
1(
#160000
1+
b101011111010000 ,
1-
1%
#170000
0%
0(
#180000
0-
b1 *
1%
#190000
0%
#200000
0$
b1 .
b0 *
1%
#210000
0%
#220000
b1 *
1%
#230000
0%
#240000
0"
b10 .
b0 *
1%
#250000
0%
#260000
b1 *
1%
#270000
0%
#280000
1#
1"
b11 .
b0 *
1%
#290000
0%
#300000
b1 *
1%
#310000
0%
#320000
0"
b100 .
b0 *
1%
#330000
0%
#340000
b1 *
1%
#350000
0%
#360000
0#
1"
b101 .
b0 *
1%
#370000
0%
#380000
b1 *
1%
#390000
0%
#400000
0"
b110 .
b0 *
1%
#410000
0%
#420000
b1 *
1%
#430000
0%
#440000
1#
1"
b111 .
b0 *
1%
#450000
0%
#460000
b1 *
1%
#470000
0%
#480000
0"
b1000 .
b0 *
1%
#490000
0%
#500000
b1 *
1%
#510000
0%
#520000
0#
1"
b1001 .
b0 *
1%
#530000
0%
#540000
b1 *
1%
#550000
0%
#560000
0"
b1010 .
b0 *
1%
#570000
0%
#580000
b1 *
1%
#590000
0%
#600000
1#
1"
b1011 .
b0 *
1%
#610000
0%
#620000
b1 *
1%
#630000
0%
#640000
0"
b1100 .
b0 *
1%
#650000
0%
#660000
b1 *
1%
#670000
0%
#680000
1"
b1101 .
b0 *
1%
#690000
0%
#700000
b1 *
1%
#710000
0%
#720000
0"
b1110 .
b0 *
1%
#730000
0%
#740000
b1 *
1%
#750000
0%
#760000
1"
b1111 .
b0 *
1%
#770000
0%
#780000
b1 *
1%
#790000
0%
#800000
0"
b10000 .
b0 *
1%
#810000
0%
#820000
b1 *
1%
#830000
0%
#840000
1"
b10001 .
b0 *
1%
#850000
0%
#860000
b1 *
1%
#870000
0%
#880000
0"
b10010 .
b0 *
1%
#890000
0%
#900000
b1 *
1%
#910000
0%
#920000
1"
b10011 .
b0 *
1%
#930000
0%
#940000
b1 *
1%
#950000
0%
#960000
0"
b10100 .
b0 *
1%
#970000
0%
#980000
b1 *
1%
#990000
0%
#1000000
0#
1"
b10101 .
b0 *
1%
#1010000
0%
#1020000
b1 *
1%
#1030000
0%
#1040000
0"
b10110 .
b0 *
1%
#1050000
0%
#1060000
b1 *
1%
#1070000
0%
#1080000
1#
1"
b10111 .
b0 *
1%
#1090000
0%
#1100000
b1 *
1%
#1110000
0%
#1120000
0"
b11000 .
b0 *
1%
#1130000
0%
#1140000
b1 *
1%
#1150000
0%
#1160000
0#
1"
b11001 .
b0 *
1%
#1170000
0%
#1180000
b1 *
1%
#1190000
0%
#1200000
0"
b11010 .
b0 *
1%
#1210000
0%
#1220000
b1 *
1%
#1230000
0%
#1240000
1"
b11011 .
b0 *
1%
#1250000
0%
#1260000
b1 *
1%
#1270000
0%
#1280000
0"
b11100 .
b0 *
1%
#1290000
0%
#1300000
b1 *
1%
#1310000
0%
#1320000
1"
b11101 .
b0 *
1%
#1330000
0%
#1340000
b1 *
1%
#1350000
0%
#1360000
0"
b11110 .
b0 *
1%
#1370000
0%
#1380000
b1 *
1%
#1390000
0%
#1400000
1"
b11111 .
b0 *
1%
#1410000
0%
#1420000
b1 *
1%
#1430000
0%
#1440000
0"
b100000 .
b0 *
1%
#1450000
0%
#1460000
b1 *
1%
#1470000
0%
#1480000
1"
b100001 .
b0 *
1%
#1490000
0%
#1500000
b1 *
1%
#1510000
0%
#1520000
1$
1!
0+
b0 .
b0 *
1%
#1530000
0%
#1540000
0!
1%
#1550000
0%
#1560000
1%
#1570000
0%
#1580000
1%
#1590000
0%
#1600000
1%
#1610000
0%
#1620000
1%
#1630000
0%
#1640000
1%
#1650000
0%
#1660000
1%
#1670000
0%
#1680000
1%
#1690000
0%
#1700000
1%
#1710000
0%
#1720000
1+
b1100001111101000 ,
1-
1%
b1100001111101000 '
b1100001111101000 )
1(
#1730000
0%
#1740000
0-
b1 *
1%
0(
#1750000
0%
#1760000
1#
0$
b1 .
b0 *
1%
#1770000
0%
#1780000
b1 *
1%
#1790000
0%
#1800000
0"
b10 .
b0 *
1%
#1810000
0%
#1820000
b1 *
1%
#1830000
0%
#1840000
1"
b11 .
b0 *
1%
#1850000
0%
#1860000
b1 *
1%
#1870000
0%
#1880000
0"
b100 .
b0 *
1%
#1890000
0%
#1900000
b1 *
1%
#1910000
0%
#1920000
0#
1"
b101 .
b0 *
1%
#1930000
0%
#1940000
b1 *
1%
#1950000
0%
#1960000
0"
b110 .
b0 *
1%
#1970000
0%
#1980000
b1 *
1%
#1990000
0%
#2000000
1"
b111 .
b0 *
1%
#2010000
0%
#2020000
b1 *
1%
#2030000
0%
#2040000
0"
b1000 .
b0 *
1%
#2050000
0%
#2060000
b1 *
1%
#2070000
0%
#2080000
1"
b1001 .
b0 *
1%
#2090000
0%
#2100000
b1 *
1%
#2110000
0%
#2120000
0"
b1010 .
b0 *
1%
#2130000
0%
#2140000
b1 *
1%
#2150000
0%
#2160000
1"
b1011 .
b0 *
1%
#2170000
0%
#2180000
b1 *
1%
#2190000
0%
#2200000
0"
b1100 .
b0 *
1%
#2210000
0%
#2220000
b1 *
1%
#2230000
0%
#2240000
1#
1"
b1101 .
b0 *
1%
#2250000
0%
#2260000
b1 *
1%
#2270000
0%
#2280000
0"
b1110 .
b0 *
1%
#2290000
0%
#2300000
b1 *
1%
#2310000
0%
#2320000
1"
b1111 .
b0 *
1%
#2330000
0%
#2340000
b1 *
1%
#2350000
0%
#2360000
0"
b10000 .
b0 *
1%
#2370000
0%
#2380000
b1 *
1%
#2390000
0%
#2400000
1"
b10001 .
b0 *
1%
#2410000
0%
#2420000
b1 *
1%
#2430000
0%
#2440000
0"
b10010 .
b0 *
1%
#2450000
0%
#2460000
b1 *
1%
#2470000
0%
#2480000
1"
b10011 .
b0 *
1%
#2490000
0%
#2500000
b1 *
1%
#2510000
0%
#2520000
0"
b10100 .
b0 *
1%
#2530000
0%
#2540000
b1 *
1%
#2550000
0%
#2560000
1"
b10101 .
b0 *
1%
#2570000
0%
#2580000
b1 *
1%
#2590000
0%
#2600000
0"
b10110 .
b0 *
1%
#2610000
0%
#2620000
b1 *
1%
#2630000
0%
#2640000
0#
1"
b10111 .
b0 *
1%
#2650000
0%
#2660000
b1 *
1%
#2670000
0%
#2680000
0"
b11000 .
b0 *
1%
#2690000
0%
#2700000
b1 *
1%
#2710000
0%
#2720000
1#
1"
b11001 .
b0 *
1%
#2730000
0%
#2740000
b1 *
1%
#2750000
0%
#2760000
0"
b11010 .
b0 *
1%
#2770000
0%
#2780000
b1 *
1%
#2790000
0%
#2800000
0#
1"
b11011 .
b0 *
1%
#2810000
0%
#2820000
b1 *
1%
#2830000
0%
#2840000
0"
b11100 .
b0 *
1%
#2850000
0%
#2860000
b1 *
1%
#2870000
0%
#2880000
1"
b11101 .
b0 *
1%
#2890000
0%
#2900000
b1 *
1%
#2910000
0%
#2920000
0"
b11110 .
b0 *
1%
#2930000
0%
#2940000
b1 *
1%
#2950000
0%
#2960000
1"
b11111 .
b0 *
1%
#2970000
0%
#2980000
b1 *
1%
#2990000
0%
#3000000
0"
b100000 .
b0 *
1%
#3010000
0%
#3020000
b1 *
1%
#3030000
0%
#3040000
1"
b100001 .
b0 *
1%
#3050000
0%
#3060000
b1 *
1%
#3070000
0%
#3080000
1$
1!
0+
b0 .
b0 *
1%
#3090000
0%
#3100000
0!
1%
